adafruit_adg72x.py
adafruit_circuitpython_adg72x-1.0.5.dist-info/licenses/LICENSE
adafruit_circuitpython_adg72x-1.0.5.dist-info/METADATA
adafruit_circuitpython_adg72x-1.0.5.dist-info/WHEEL
adafruit_circuitpython_adg72x-1.0.5.dist-info/top_level.txt
adafruit_circuitpython_adg72x-1.0.5.dist-info/RECORD
