Metadata-Version: 2.4
Name: adafruit-circuitpython-adg72x
Version: 1.0.5
Summary: CircuitPython driver for the ADG728 and ADG729 analog matrix switches.
Author-email: Adafruit Industries <circuitpython@adafruit.com>
License: MIT
Project-URL: Homepage, https://github.com/adafruit/Adafruit_CircuitPython_ADG72x
Keywords: adafruit,blinka,circuitpython,micropython,adg72x,adg728,adg729
Classifier: Intended Audience :: Developers
Classifier: Topic :: Software Development :: Libraries
Classifier: Topic :: Software Development :: Embedded Systems
Classifier: Topic :: System :: Hardware
Classifier: License :: OSI Approved :: MIT License
Classifier: Programming Language :: Python :: 3
License-File: LICENSE
Requires-Dist: Adafruit-Blinka
Requires-Dist: adafruit-circuitpython-busdevice
Provides-Extra: optional
Dynamic: license-file
